geocoder_reverse_natural_earth/__init__.py
geocoder_reverse_natural_earth/geocoder_reverse_ne.py
geocoder_reverse_natural_earth/ne_10m_admin_0_countries_deu.zip
geocoder_reverse_natural_earth-0.0.2.dist-info/LICENSE
geocoder_reverse_natural_earth-0.0.2.dist-info/METADATA
geocoder_reverse_natural_earth-0.0.2.dist-info/WHEEL
geocoder_reverse_natural_earth-0.0.2.dist-info/top_level.txt
geocoder_reverse_natural_earth-0.0.2.dist-info/RECORD
