Metadata-Version: 2.1
Name: geocoder_reverse_natural_earth
Version: 0.0.2
Summary: implementations of geocoder_reverse using natural_earth shape-files
Home-page: https://github.com/metno/geocoder_reverse_natural_earth
Author: MET Norway
Classifier: Programming Language :: Python :: 3 :: Only
Classifier: Programming Language :: Python :: 3.9
Classifier: Programming Language :: Python :: 3.10
Classifier: Programming Language :: Python :: 3.11
Classifier: License :: OSI Approved :: GNU Lesser General Public License v3 (LGPLv3)
Classifier: Operating System :: OS Independent
Classifier: Development Status :: 3 - Alpha
Classifier: Intended Audience :: Science/Research
Classifier: Intended Audience :: Education
Classifier: Topic :: Scientific/Engineering :: Atmospheric Science
License-File: LICENSE
Requires-Dist: pyaro >=0.0.6
Requires-Dist: fiona
Requires-Dist: shapely
Requires-Dist: rtree
